{
    "Description": "本文件存储了瓦片服务器发布的相关图层信息",
    "version": "1.0.0",
    "Author": "liyunfei",
    "Layers": [
        {
            "ProjectionType": "EQ",
            "Title": "好奇号区域高分影像",
            "LayerID": "Mars_curiosity_ctx_mosaic",
            "Icon": "{MarsImage}\\Mars_curiosity_ctx_mosaic\\curiosity_ctx_mosaic-120.png",
            "BBOX": [
                136.2768326,-7.2137273,139.3864225,-3.5804738
            ],
            "Abstract": "这些数据是使用美国宇航局火星勘测轨道飞行器 (MRO) 上的上下文相机获取的。 MRO 于 2005 年 8 月 12 日发射，并于 2006 年 3 月 10 日抵达火星。它保持近乎圆形的轨道，在大约 250 至 316 公里或 155 至 196 英里的高度上大约每 112 分钟完成一次轨道公转。 MRO 携带一套精密的仪器，用于分析和绘制火星的地貌、地层、矿物和冰。 Context Camera (CTX) 提供分辨率高达 6 米/像素的黑白图像。它为 HiRISE 相机以及 MRO 上的其他仪器提供更高分辨率但更窄的视野的更广泛的上下文地图，并且对于生成火星表面更大区域的镶嵌图像很有用。",
            "Projection": "urn:ogc:def:crs:EPSG::104905",
            "Preview": "{MarsImage}\\Mars_curiosity_ctx_mosaic\\index.html",
            "WMTS_Capabiliites": "{MarsImage}\\Mars_curiosity_ctx_mosaic\\WMTSCapabilities.xml",
            "MetaData": "{MarsImage}\\Mars_curiosity_ctx_mosaic\\metadata.html"
        },
        {
            "ProjectionType": "EQ",
            "Title": "好奇号区域高分影像",
            "LayerID": "Mars_MGS_MOLA_ClrShade_merge_global_463m",
            "Icon": "{MarsImage}\\Mars_MGS_MOLA_ClrShade_merge_global_463m\\Mars_MGS_MOLA_ClrShade_merge_global_463m-120.png",
            "BBOX": [
                -180,-90,180,90
            ],
            "Abstract":"这些数据是使用美国宇航局火星全球勘测者航天器（MGS）上的火星轨道器激光高度计仪器获取的。MGS于1996年11月7日发射升空，并于1997年9月11日抵达火星。它保持了一个圆形的极轨道，每117.65分钟完成一次轨道公转，平均高度为378公里（235英里）。直到2006年11月2日，MGS对火星表面特征，性质，地形，组成和过程进行了表征和绘制，并研究了火星的天气和大气结构。火星轨道器激光高度计（MOLA）对火星表面特征的高度和深度进行了精确测量。MOLA每秒向下发射10次红外激光脉冲，并测量反射脉冲从表面返回所需的时间。将此数据转换为彩色山体阴影使得可视化表面地形变得特别容易。用于此地图底部的图像代表了 1999 年至 2001 年间收集的 6 亿多个测量值。每个点的平均精度最初在水平位置为~100米，总高程不确定性至少为±3米。",
            "Projection": "urn:ogc:def:crs:EPSG::104905",
            "Preview": "{MarsImage}\\Mars_MGS_MOLA_ClrShade_merge_global_463m\\index.html",
            "WMTS_Capabiliites": "{MarsImage}\\Mars_MGS_MOLA_ClrShade_merge_global_463m\\WMTSCapabilities.xml",
            "MetaData": "{MarsImage}\\Mars_MGS_MOLA_ClrShade_merge_global_463m\\metadata.html"
        },
        {
            "ProjectionType": "EQ",
            "Title": "火星全球影像(海盗号)",
            "LayerID": "Mars_Viking_MDIM21_ClrMosaic_global_232m",
            "Icon": "{MarsImage}\\Mars_Viking_MDIM21_ClrMosaic_global_232m\\Mars_Viking_MDIM21_ClrMosaic_global_232m-120.png",
            "BBOX": [
                -180,-90,180,90
            ],
            "Abstract": "该产品是根据使用维京1号和维京2号轨道器上的维京轨道器成像系统收集的数据组装而成的。两个轨道器上的相同视频相机都配备了475毫米焦距的长焦镜头，产生1.54бу X 1.69бу的视野。从 1500 公里的轨道高度开始，每帧覆盖 40 X 44 公里表面上的最小区域。六个可选滤光片允许采集彩色图像。",
            "Projection": "urn:ogc:def:crs:EPSG::104905",
            "Preview": "{MarsImage}\\Mars_Viking_MDIM21_ClrMosaic_global_232m\\index.html",
            "WMTS_Capabiliites": "{MarsImage}\\Mars_Viking_MDIM21_ClrMosaic_global_232m\\WMTSCapabilities.xml",
            "MetaData": "{MarsImage}\\Mars_Viking_MDIM21_ClrMosaic_global_232m\\metadata.html"
        }
    ]
}